CRC/__init__.py
CRC/crcDecoder.py
CRC/crcEncoder.py
ChannelCoder/__init__.py
ChannelCoder/LDPC/__init__.py
ChannelCoder/LDPC/ldpcDecoder5G (copy).py
ChannelCoder/LDPC/ldpcDecoder5G.py
ChannelCoder/LDPC/ldpcEncoder5G (copy).py
ChannelCoder/LDPC/ldpcEncoder5G.py
ChannelCoder/LDPC/ldpcParameters.py
ChannelCoder/LDPC/CodeblockProcessing/codeBlockAggregation.py
ChannelCoder/LDPC/CodeblockProcessing/codeBlockConcatenation.py
ChannelCoder/LDPC/CodeblockProcessing/codeBlockSegmentation.py
ChannelCoder/LDPC/CodeblockProcessing/codeBlockSegregation.py
ChannelCoder/LDPC/codes/__init__.py
ChannelCoder/PolarCoder/__init__.py
ChannelCoder/PolarCoder/polar5GDecoder.py
ChannelCoder/PolarCoder/polar5GEncoder.py
ChannelCoder/PolarCoder/polarDecoder.py
ChannelCoder/PolarCoder/polarDecoder5G.py
ChannelCoder/PolarCoder/polarEncoder.py
ChannelCoder/PolarCoder/polarEncoder5G.py
ChannelCoder/PolarCoder/CodeblockProcessing/codeBlockAggregation.py
ChannelCoder/PolarCoder/CodeblockProcessing/codeBlockConcatenation.py
ChannelCoder/PolarCoder/CodeblockProcessing/codeBlockSegmentation.py
ChannelCoder/PolarCoder/CodeblockProcessing/codeBlockSegregation.py
ChannelCoder/PolarCoder/Interleaver/inputBitDeInterleaver.py
ChannelCoder/PolarCoder/Interleaver/inputBitInterleaver.py
ChannelCoder/ReedMullerCoder/__init__.py
ChannelCoder/ReedMullerCoder/reedMullerDecoder5G.py
ChannelCoder/ReedMullerCoder/reedMullerEncoder5G.py
ChannelProcessing/__init__.py
ChannelProcessing/addNoise.py
ChannelProcessing/applyChannel.py
Configurations/__init__.py
Configurations/ts38_1x/timeFrequency_5GParameters.py
Configurations/ts38_2x/generateValidSSBParameters.py
MIMOProcessing/__init__.py
MIMOProcessing/analogBeamforming.py
MIMOProcessing/digitalBeamforming.py
MIMOProcessing/precoding.py
MIMOProcessing/receiveCombining.py
OFDM/__init__.py
OFDM/ofdmDemodulator.py
OFDM/ofdmModulator.py
PayloadGeneration/__init__.py
PayloadGeneration/DCI/dciExtraction.py
PayloadGeneration/DCI/dciGeneration.py
Toolkit_5G-0.0.0.4.dist-info/LICENSE
Toolkit_5G-0.0.0.4.dist-info/METADATA
Toolkit_5G-0.0.0.4.dist-info/WHEEL
Toolkit_5G-0.0.0.4.dist-info/top_level.txt
Toolkit_5G-0.0.0.4.dist-info/RECORD
