Metadata-Version: 2.1
Name: Toolkit-5G
Version: 0.0.0.4
Summary: A Toolkit package written in python for 5G NR
Author-email: VijayGigayasa <vijaya@gigayasa.com>
Project-URL: Homepage, https://gigayasawireless.github.io/5GToolkit/index.html
Project-URL: Bug Tracker, https://github.com/pypa/5GToolkit/issues
Classifier: Programming Language :: Python :: 3
Classifier: License :: OSI Approved :: MIT License
Classifier: Operating System :: OS Independent
Requires-Python: >=3.7
License-File: LICENSE
Requires-Dist: tensorflow
Requires-Dist: numpy
Requires-Dist: matplotlib
Requires-Dist: ipympl
